{"encodedAci":{"contract":{"functions":[{"arguments":[],"name":"init","payable":false,"returns":"VoiceAeds.state","stateful":true},{"arguments":[],"name":"get_voice_records","payable":false,"returns":{"map":["int","VoiceAeds.voice_meta"]},"stateful":false},{"arguments":[],"name":"deposit_to_contract","payable":true,"returns":"int","stateful":true},{"arguments":[],"name":"check_contract_balance","payable":false,"returns":"int","stateful":true},{"arguments":[],"name":"check_contract_address","payable":false,"returns":"address","stateful":true},{"arguments":[{"name":"link","type":"string"},{"name":"reward","type":"int"},{"name":"max_reward","type":"int"},{"name":"answer","type":"string"}],"name":"create_voice_record","payable":false,"returns":"bool","stateful":true},{"arguments":[{"name":"id","type":"int"}],"name":"delete_voice_record","payable":false,"returns":"bool","stateful":true},{"arguments":[{"name":"id","type":"int"},{"name":"link","type":"string"},{"name":"reward","type":"int"},{"name":"max_reward","type":"int"},{"name":"answer","type":"string"}],"name":"update_voice_record","payable":false,"returns":"bool","stateful":true},{"arguments":[{"name":"id","type":"int"},{"name":"ans","type":"string"}],"name":"answer_question","payable":false,"returns":"bool","stateful":true},{"arguments":[],"name":"clear_completed_player","payable":false,"returns":"bool","stateful":true}],"kind":"contract_main","name":"VoiceAeds","payable":false,"state":{"record":[{"name":"index","type":"int"},{"name":"completed_player","type":{"map":["address","int"]}},{"name":"voice_records","type":{"map":["int","VoiceAeds.voice_meta"]}},{"name":"deployer","type":"address"}]},"type_defs":[{"name":"voice_meta","typedef":{"record":[{"name":"voice_link","type":"string"},{"name":"reward","type":"int"},{"name":"max_reward","type":"int"},{"name":"answer","type":"string"},{"name":"id","type":"int"}]},"vars":[]}]}},"externalEncodedAci":[],"interface":"main contract VoiceAeds =\n  record state = {index : int,completed_player : map(address, int),voice_records : map(int, VoiceAeds.voice_meta),deployer : address}\n  record voice_meta = {voice_link : string,reward : int,max_reward : int,answer : string,id : int}\n  stateful entrypoint init : () => VoiceAeds.state\n  entrypoint get_voice_records : () => map(int, VoiceAeds.voice_meta)\n  payable stateful entrypoint deposit_to_contract : () => int\n  stateful entrypoint check_contract_balance : () => int\n  stateful entrypoint check_contract_address : () => address\n  stateful entrypoint create_voice_record : (string, int, int, string) => bool\n  stateful entrypoint delete_voice_record : (int) => bool\n  stateful entrypoint update_voice_record : (int, string, int, int, string) => bool\n  stateful entrypoint answer_question : (int, string) => bool\n  stateful entrypoint clear_completed_player : () => bool\n"}